pnvdb/__init__.py
pnvdb/config.py
pnvdb/const.py
pnvdb/datafangst.py
pnvdb/les.py
pnvdb/models/__init__.py
pnvdb/models/area.py
pnvdb/models/feature.py
pnvdb/models/feature_collection.py
pnvdb/models/objekt.py
pnvdb/models/objekt_type.py
pnvdb/models/pnvdb_exceptions.py
pnvdb/models/posisjon.py
pnvdb/models/util.py
pnvdb/models/vegreferanse.py
pnvdb-0.4.0.dist-info/METADATA
pnvdb-0.4.0.dist-info/RECORD
pnvdb-0.4.0.dist-info/WHEEL
pnvdb-0.4.0.dist-info/top_level.txt
