Metadata-Version: 2.1
Name: pnvdb
Version: 0.4.0
Summary: A python wrapper for the NVDB REST API
Home-page: http://pnvdb.readthedocs.io/
Author: Jan Tore Kyrdalen
Author-email: kyrdalen.no@gmail.com
License: MIT
Requires-Dist: requests
Requires-Dist: geojson
